{
  "persons": [
    {
      "name": "Arto Hellas",
      "number": "040-123456",
      "id": 1
    },
    {
      "name": "Ada Lovelace",
      "number": "39-44-5323523",
      "id": 2
    },
    {
      "name": "Dan Abramov",
      "number": "12-43-234345",
      "id": 3
    },
    {
      "name": "natnael Yacob",
      "number": "0415697457",
      "id": 5
    },
    {
      "name": "dina yacob",
      "number": "07118808",
      "id": 8
    },
    {
      "name": "enter the name",
      "number": "123",
      "id": 9
    },
    {
      "name": "candy",
      "number": "1234",
      "id": 10
    }
  ]
}